[
  {
    "Type": "DataTable",
    "Name": "DT_FurnitureFortuneDataTable",
    "Class": "UScriptClass'DataTable'",
    "Flags": "RF_Public | RF_Standalone | RF_Transactional | RF_WasLoaded | RF_LoadCompleted",
    "Properties": {
      "RowStruct": {
        "ObjectName": "ScriptStruct'FurnitureAttributeData'",
        "ObjectPath": "/Script/HTGame"
      }
    },
    "Rows": {
      "1": {
        "Level": 1,
        "Desc": {
          "TableId": "/Game/Text/ST_Clone.ST_Clone",
          "Key": "DLC_Hockshop_Name",
          "SourceString": "月光当铺",
          "LocalizedString": "月光当铺"
        },
        "Value": 100,
        "Addition": 4.0,
        "TimeInterval": 0.0
      },
      "2": {
        "Level": 2,
        "Desc": {
          "TableId": "/Game/Text/ST_Clone.ST_Clone",
          "Key": "Clonetype_gold",
          "SourceString": "<!>金币本",
          "LocalizedString": "<!>金币本"
        },
        "Value": 200,
        "Addition": 8.0,
        "TimeInterval": 0.0
      },
      "3": {
        "Level": 3,
        "Desc": {
          "TableId": "/Game/Text/ST_Clone.ST_Clone",
          "Key": "Clonetype_wpexp",
          "SourceString": "<!>弧盘经验本",
          "LocalizedString": "<!>弧盘经验本"
        },
        "Value": 300,
        "Addition": 12.0,
        "TimeInterval": 0.0
      },
      "4": {
        "Level": 4,
        "Desc": {
          "TableId": "/Game/Text/ST_Clone.ST_Clone",
          "Key": "Clonetype_wpexp",
          "SourceString": "<!>弧盘经验本",
          "LocalizedString": "<!>弧盘经验本"
        },
        "Value": 400,
        "Addition": 16.0,
        "TimeInterval": 0.0
      },
      "5": {
        "Level": 5,
        "Desc": {
          "TableId": "/Game/Text/ST_Clone.ST_Clone",
          "Key": "Clonetype_wpexp",
          "SourceString": "<!>弧盘经验本",
          "LocalizedString": "<!>弧盘经验本"
        },
        "Value": 500,
        "Addition": 20.0,
        "TimeInterval": 0.0
      },
      "6": {
        "Level": 6,
        "Desc": {
          "TableId": "/Game/Text/ST_Clone.ST_Clone",
          "Key": "Clonetype_wpexp",
          "SourceString": "<!>弧盘经验本",
          "LocalizedString": "<!>弧盘经验本"
        },
        "Value": 600,
        "Addition": 24.0,
        "TimeInterval": 0.0
      },
      "7": {
        "Level": 7,
        "Desc": {
          "TableId": "/Game/Text/ST_Clone.ST_Clone",
          "Key": "Clonetype_wpexp",
          "SourceString": "<!>弧盘经验本",
          "LocalizedString": "<!>弧盘经验本"
        },
        "Value": 700,
        "Addition": 28.0,
        "TimeInterval": 0.0
      },
      "8": {
        "Level": 8,
        "Desc": {
          "TableId": "/Game/Text/ST_Clone.ST_Clone",
          "Key": "Clonetype_wpexp",
          "SourceString": "<!>弧盘经验本",
          "LocalizedString": "<!>弧盘经验本"
        },
        "Value": 800,
        "Addition": 32.0,
        "TimeInterval": 0.0
      },
      "9": {
        "Level": 9,
        "Desc": {
          "TableId": "/Game/Text/ST_Clone.ST_Clone",
          "Key": "Clonetype_wpexp",
          "SourceString": "<!>弧盘经验本",
          "LocalizedString": "<!>弧盘经验本"
        },
        "Value": 900,
        "Addition": 36.0,
        "TimeInterval": 0.0
      },
      "10": {
        "Level": 10,
        "Desc": {
          "TableId": "/Game/Text/ST_Clone.ST_Clone",
          "Key": "Clonetype_wpexp",
          "SourceString": "<!>弧盘经验本",
          "LocalizedString": "<!>弧盘经验本"
        },
        "Value": 1000,
        "Addition": 40.0,
        "TimeInterval": 0.0
      }
    }
  }
]