[
  {
    "Type": "DataTable",
    "Name": "DT_ShowCaseCycle",
    "Class": "UScriptClass'DataTable'",
    "Flags": "RF_Public | RF_Standalone | RF_Transactional | RF_WasLoaded | RF_LoadCompleted",
    "Properties": {
      "RowStruct": {
        "ObjectName": "ScriptStruct'ShowCaseCycle'",
        "ObjectPath": "/Script/HTGame"
      }
    },
    "Rows": {
      "collection_000": {
        "DropID": "drop_q110022"
      },
      "collection_001": {
        "DropID": "drop_q110022"
      },
      "collection_002": {
        "DropID": "drop_q110022"
      },
      "collection_003": {
        "DropID": "drop_q110022"
      },
      "collection_004": {
        "DropID": "drop_q110022"
      }
    }
  }
]